{
 "accept_payment": 0, 
 "allow_comments": 0, 
 "allow_delete": 0, 
 "allow_edit": 0, 
 "allow_incomplete": 1, 
 "allow_multiple": 0, 
 "allow_print": 0, 
 "amount": 0.0, 
 "amount_based_on_field": 0, 
 "creation": "2017-01-30 16:41:12.723947", 
 "currency": "INR", 
 "doc_type": "Payment Details", 
 "docstatus": 0, 
 "doctype": "Web Form", 
 "idx": 0, 
 "is_standard": 1, 
 "login_required": 0, 
 "max_attachment_size": 0, 
 "modified": "2017-02-07 16:12:24.595975", 
 "modified_by": "Administrator", 
 "module": "Car Emi", 
 "name": "payment-details", 
 "owner": "Administrator", 
 "payment_button_label": "Buy Now", 
 "published": 1, 
 "route": "payment-details", 
 "show_sidebar": 1, 
 "sidebar_items": [], 
 "success_url": "/payment-details", 
 "title": "Payment Details", 
 "web_form_fields": [
  {
   "fieldname": "total_amount", 
   "fieldtype": "Data", 
   "hidden": 0, 
   "label": "Total Amount", 
   "max_length": 0, 
   "max_value": 0, 
   "read_only": 0, 
   "reqd": 0
  }, 
  {
   "fieldname": "loan_required", 
   "fieldtype": "Check", 
   "hidden": 0, 
   "label": "Loan Required", 
   "max_length": 0, 
   "max_value": 0, 
   "read_only": 0, 
   "reqd": 0
  }, 
  {
   "fieldname": "bank_name", 
   "fieldtype": "Select", 
   "hidden": 0, 
   "label": "Bank Name", 
   "max_length": 0, 
   "max_value": 0, 
   "options": "SBI\nHDFC\nICICI\nAxis\n", 
   "read_only": 0, 
   "reqd": 0
  }, 
  {
   "fieldname": "loan_duration", 
   "fieldtype": "Select", 
   "hidden": 0, 
   "label": "Loan Duration", 
   "max_length": 0, 
   "max_value": 0, 
   "options": "24 months\n36 months\n48 months\n60 months\n84 months", 
   "read_only": 0, 
   "reqd": 1
  }, 
  {
   "fieldname": "interest_rate", 
   "fieldtype": "Float", 
   "hidden": 0, 
   "label": "Interest Rate", 
   "max_length": 0, 
   "max_value": 0, 
   "read_only": 0, 
   "reqd": 1
  }, 
  {
   "fieldname": "down_payment", 
   "fieldtype": "Data", 
   "hidden": 0, 
   "label": "Down Payment", 
   "max_length": 0, 
   "max_value": 0, 
   "read_only": 0, 
   "reqd": 1
  }, 
  {
   "fieldname": "loan_amount", 
   "fieldtype": "Data", 
   "hidden": 0, 
   "label": "Loan Amount", 
   "max_length": 0, 
   "max_value": 0, 
   "read_only": 0, 
   "reqd": 0
  }, 
  {
   "fieldname": "emi", 
   "fieldtype": "Data", 
   "hidden": 0, 
   "label": "EMI", 
   "max_length": 0, 
   "max_value": 0, 
   "read_only": 0, 
   "reqd": 0
  }
 ]
}